LICENSE
MANIFEST.in
README.rst
setup.py
sortedmap/__init__.py
sortedmap/_sortedmap.cpp
sortedmap.egg-info/PKG-INFO
sortedmap.egg-info/SOURCES.txt
sortedmap.egg-info/dependency_links.txt
sortedmap.egg-info/requires.txt
sortedmap.egg-info/top_level.txt
sortedmap/include/sortedmap.h