Metadata-Version: 1.1
Name: sortedmap
Version: 0.1.0
Summary: A sorted mapping object
Home-page: https://github.com/llllllllll/sortedmap
Author: Joe Jevnik
Author-email: joejev@gmail.com
License: LGPLv2
Platform: UNKNOWN
Classifier: Development Status :: 3 - Alpha
Classifier: Intended Audience :: Developers
Classifier: License :: OSI Approved :: GNU Lesser General Public License v2 (LGPLv2)
Classifier: Natural Language :: English
Classifier: Programming Language :: C++
Classifier: Programming Language :: Python :: 2
Classifier: Programming Language :: Python :: 3
Classifier: Programming Language :: Python :: Implementation :: CPython
